<?xml version="1.0" encoding="UTF-8"?><record_update sys_domain="global" table="sys_ux_page_property">
    <sys_ux_page_property action="DELETE">
        <choices/>
        <description/>
        <name>enable_login_modal</name>
        <page display_value="">4e50321347500a1004c8d44a516d43a2</page>
        <required_translations/>
        <route/>
        <suffix/>
        <sys_class_name>sys_ux_page_property</sys_class_name>
        <sys_created_by>system</sys_created_by>
        <sys_created_on>2024-02-17 05:54:08</sys_created_on>
        <sys_domain>global</sys_domain>
        <sys_domain_path>global</sys_domain_path>
        <sys_id>5e50321337500a108fcb293f366952c7</sys_id>
        <sys_mod_count>0</sys_mod_count>
        <sys_name>enable_login_modal</sys_name>
        <sys_package display_value="Loaner Vehicle Request and Inventory" source="x_1298059_loaner_0">49a969ca4733311004c8d44a516d4372</sys_package>
        <sys_policy/>
        <sys_scope display_value="Loaner Vehicle Request and Inventory">49a969ca4733311004c8d44a516d4372</sys_scope>
        <sys_update_name>sys_ux_page_property_5e50321337500a108fcb293f366952c7</sys_update_name>
        <sys_updated_by>system</sys_updated_by>
        <sys_updated_on>2024-02-17 05:54:08</sys_updated_on>
        <type>json</type>
        <unique_name>x_1298059_loaner_0.4e50321347500a1004c8d44a516d43a2.root.enable_login_modal</unique_name>
        <value>{&#13;
	"enabled":false&#13;
}</value>
    </sys_ux_page_property>
    <sys_update_version action="INSERT_OR_UPDATE">
        <action>DELETE</action>
        <application display_value="Loaner Vehicle Request and Inventory">49a969ca4733311004c8d44a516d4372</application>
        <file_path/>
        <instance_id>a503c7ccdb1a31d402022a591396199a</instance_id>
        <instance_name>dev198269</instance_name>
        <name>sys_ux_page_property_5e50321337500a108fcb293f366952c7</name>
        <payload><![CDATA[<?xml version="1.0" encoding="UTF-8"?><record_update sys_domain="global" table="sys_ux_page_property"><sys_ux_page_property action="INSERT_OR_UPDATE"><choices/><description/><name>enable_login_modal</name><page display_value="">4e50321347500a1004c8d44a516d43a2</page><required_translations/><route/><suffix/><sys_class_name>sys_ux_page_property</sys_class_name><sys_created_by>system</sys_created_by><sys_created_on>2024-02-17 05:54:08</sys_created_on><sys_domain>global</sys_domain><sys_domain_path>global</sys_domain_path><sys_id>5e50321337500a108fcb293f366952c7</sys_id><sys_mod_count>0</sys_mod_count><sys_name>enable_login_modal</sys_name><sys_package display_value="Loaner Vehicle Request and Inventory" source="x_1298059_loaner_0">49a969ca4733311004c8d44a516d4372</sys_package><sys_policy/><sys_scope display_value="Loaner Vehicle Request and Inventory">49a969ca4733311004c8d44a516d4372</sys_scope><sys_update_name>sys_ux_page_property_5e50321337500a108fcb293f366952c7</sys_update_name><sys_updated_by>system</sys_updated_by><sys_updated_on>2024-02-17 05:54:08</sys_updated_on><type>json</type><unique_name>x_1298059_loaner_0.4e50321347500a1004c8d44a516d43a2.root.enable_login_modal</unique_name><value>{&#13;
	"enabled":false&#13;
}</value></sys_ux_page_property></record_update>]]></payload>
        <payload_hash>717190255</payload_hash>
        <record_name>enable_login_modal</record_name>
        <reverted_from/>
        <source>498044334700021004c8d44a516d43b3</source>
        <source_table>sys_upgrade_history</source_table>
        <state>previous</state>
        <sys_created_by/>
        <sys_created_on>2024-02-05 20:07:09</sys_created_on>
        <sys_id>5ffbfe9f47500a1004c8d44a516d439d</sys_id>
        <sys_mod_count/>
        <sys_recorded_at>18d7ae1b5c80000000</sys_recorded_at>
        <sys_updated_by/>
        <sys_updated_on/>
        <type>UX Page Property</type>
        <update_guid>1ffbfe9f70500a10824399844d46449d</update_guid>
        <update_guid_history>1ffbfe9f70500a10824399844d46449d:717190255</update_guid_history>
    </sys_update_version>
    <sys_metadata_delete action="INSERT_OR_UPDATE">
        <sys_audit_delete/>
        <sys_class_name>sys_metadata_delete</sys_class_name>
        <sys_created_by>system</sys_created_by>
        <sys_created_on>2024-02-17 06:44:59</sys_created_on>
        <sys_db_object display_value="" name="sys_ux_page_property">sys_ux_page_property</sys_db_object>
        <sys_id>5da35f5470af48188cf6b6a8fe3732b9</sys_id>
        <sys_metadata>5e50321337500a108fcb293f366952c7</sys_metadata>
        <sys_mod_count>0</sys_mod_count>
        <sys_name>enable_login_modal</sys_name>
        <sys_package display_value="Loaner Vehicle Request and Inventory" source="x_1298059_loaner_0">49a969ca4733311004c8d44a516d4372</sys_package>
        <sys_parent/>
        <sys_policy/>
        <sys_scope display_value="Loaner Vehicle Request and Inventory">49a969ca4733311004c8d44a516d4372</sys_scope>
        <sys_scope_delete display_value="">1b2ae3d0be134b3db946bc94e89b91a1</sys_scope_delete>
        <sys_update_name>sys_ux_page_property_5e50321337500a108fcb293f366952c7</sys_update_name>
        <sys_update_version display_value="sys_ux_page_property_5e50321337500a108fcb293f366952c7">5ffbfe9f47500a1004c8d44a516d439d</sys_update_version>
        <sys_updated_by>system</sys_updated_by>
        <sys_updated_on>2024-02-17 06:44:59</sys_updated_on>
    </sys_metadata_delete>
</record_update>
